fenics_ffcx-0.10.0.dist-info/licenses/COPYING
fenics_ffcx-0.10.0.dist-info/licenses/COPYING.LESSER
ffcx/__init__.py
ffcx/__main__.py
ffcx/analysis.py
ffcx/compiler.py
ffcx/definitions.py
ffcx/element_interface.py
ffcx/formatting.py
ffcx/git_commit_hash.py.in
ffcx/main.py
ffcx/naming.py
ffcx/options.py
ffcx/py.typed
ffcx/codegeneration/__init__.py
ffcx/codegeneration/access.py
ffcx/codegeneration/backend.py
ffcx/codegeneration/codegeneration.py
ffcx/codegeneration/definitions.py
ffcx/codegeneration/expression_generator.py
ffcx/codegeneration/geometry.py
ffcx/codegeneration/integral_generator.py
ffcx/codegeneration/jit.py
ffcx/codegeneration/lnodes.py
ffcx/codegeneration/optimizer.py
ffcx/codegeneration/symbols.py
ffcx/codegeneration/ufcx.h
ffcx/codegeneration/utils.py
ffcx/codegeneration/C/__init__.py
ffcx/codegeneration/C/c_implementation.py
ffcx/codegeneration/C/expressions.py
ffcx/codegeneration/C/expressions_template.py
ffcx/codegeneration/C/file.py
ffcx/codegeneration/C/file_template.py
ffcx/codegeneration/C/form.py
ffcx/codegeneration/C/form_template.py
ffcx/codegeneration/C/integrals.py
ffcx/codegeneration/C/integrals_template.py
ffcx/ir/__init__.py
ffcx/ir/elementtables.py
ffcx/ir/integral.py
ffcx/ir/representation.py
ffcx/ir/representationutils.py
ffcx/ir/analysis/__init__.py
ffcx/ir/analysis/factorization.py
ffcx/ir/analysis/graph.py
ffcx/ir/analysis/indexing.py
ffcx/ir/analysis/modified_terminals.py
ffcx/ir/analysis/reconstruct.py
ffcx/ir/analysis/valuenumbering.py
ffcx/ir/analysis/visualise.py
fenics_ffcx-0.10.0.dist-info/METADATA
fenics_ffcx-0.10.0.dist-info/WHEEL
fenics_ffcx-0.10.0.dist-info/entry_points.txt
fenics_ffcx-0.10.0.dist-info/top_level.txt
fenics_ffcx-0.10.0.dist-info/RECORD
