Metadata-Version: 2.4
Name: fenics-ffcx
Version: 0.10.0
Summary: The FEniCSx Form Compiler
Author: FEniCS Steering Council
Author-email: fenics-steering-council@googlegroups.com
License-Expression: LGPL-3.0-or-later
Project-URL: homepage, https://fenicsproject.org
Project-URL: repository, https://github.com/fenics/ffcx.git
Project-URL: documentation, https://docs.fenicsproject.org
Requires-Python: >=3.10
License-File: COPYING
License-File: COPYING.LESSER
Requires-Dist: numpy>=1.21
Requires-Dist: cffi
Requires-Dist: setuptools>=77.0.3
Requires-Dist: fenics-basix<0.11.0,>=0.10.0
Requires-Dist: fenics-ufl<2025.3.0,>=2025.2.0
Provides-Extra: lint
Requires-Dist: ruff; extra == "lint"
Provides-Extra: docs
Requires-Dist: sphinx; extra == "docs"
Requires-Dist: sphinx_rtd_theme; extra == "docs"
Provides-Extra: optional
Requires-Dist: numba; extra == "optional"
Requires-Dist: pygraphviz==1.9; extra == "optional"
Provides-Extra: test
Requires-Dist: pytest>=6.0; extra == "test"
Requires-Dist: sympy; extra == "test"
Requires-Dist: numba; extra == "test"
Provides-Extra: ci
Requires-Dist: coveralls; extra == "ci"
Requires-Dist: coverage>=7.0.0; extra == "ci"
Requires-Dist: pytest-cov; extra == "ci"
Requires-Dist: pytest-xdist; extra == "ci"
Requires-Dist: types-setuptools; extra == "ci"
Requires-Dist: mypy; extra == "ci"
Requires-Dist: fenics-ffcx[docs]; extra == "ci"
Requires-Dist: fenics-ffcx[lint]; extra == "ci"
Requires-Dist: fenics-ffcx[test]; extra == "ci"
Dynamic: license-file
